phisher/__init__.py
phisher/__main__.py
phisher/config.py
phisher/decoder.py
phisher/monitor.py
phisher/telegram_notifier.py
phisher_ctmonitor-0.1.2.dist-info/METADATA
phisher_ctmonitor-0.1.2.dist-info/WHEEL
phisher_ctmonitor-0.1.2.dist-info/entry_points.txt
phisher_ctmonitor-0.1.2.dist-info/top_level.txt
phisher_ctmonitor-0.1.2.dist-info/RECORD
