Metadata-Version: 2.4
Name: phisher-ctmonitor
Version: 0.1.2
Summary: A tool for monitoring the certificate transparency logs.
Home-page: https://github.com/nbdknws/phisher
Author: Viktoryia Valiuk
Author-email: viktoriapogorzhelska@gmail.com
Classifier: Programming Language :: Python :: 3
Classifier: Operating System :: OS Independent
Requires-Python: >=3.6
Requires-Dist: construct==2.10.70
Requires-Dist: cryptography==45.0.4
Requires-Dist: python-telegram-bot==22.2
Requires-Dist: Requests==2.32.4
Requires-Dist: rich==14.0.0
Requires-Dist: rich_argparse==1.7.1
Requires-Dist: rich_gradient==0.3.2
Dynamic: author
Dynamic: author-email
Dynamic: classifier
Dynamic: description
Dynamic: description-content-type
Dynamic: home-page
Dynamic: requires-dist
Dynamic: requires-python
Dynamic: summary
